libpolarbytebot/__init__.py
libpolarbytebot/models.py
libpolarbytebot/polarbytebot.py
libpolarbytebot/eastereggs/__init__.py
libpolarbytebot/eastereggs/overwatch.py
libpolarbytebot/tracker/__init__.py
libpolarbytebot/tracker/guildwars2.py
libpolarbytebot/tracker/formats/__init__.py
libpolarbytebot/tracker/formats/guildwars2_format.py
libpolarbytebot/transcriber/__init__.py
libpolarbytebot/transcriber/guildwars2_blog.py
libpolarbytebot/transcriber/guildwars2_forum.py
libpolarbytebot/transcriber/overwatch_forum.py
libpolarbytebot/transcriber/formats/__init__.py
libpolarbytebot/transcriber/formats/guildwars2_format.py
libpolarbytebot/transcriber/formats/overwatch_format.py
libpolarbytebot/transcriber/markdown/__init__.py
libpolarbytebot/transcriber/markdown/guildwars2_html2markdown.py
libpolarbytebot/transcriber/markdown/markdown_dictionary.py
libpolarbytebot/transcriber/markdown/overwatch_html2markdown.py
libpolarbytebot-0.7.14.dist-info/DESCRIPTION.rst
libpolarbytebot-0.7.14.dist-info/METADATA
libpolarbytebot-0.7.14.dist-info/RECORD
libpolarbytebot-0.7.14.dist-info/WHEEL
libpolarbytebot-0.7.14.dist-info/metadata.json
libpolarbytebot-0.7.14.dist-info/top_level.txt
