Metadata-Version: 2.0
Name: libpolarbytebot
Version: 0.7.14
Summary: polarbytebot core
Home-page: https://gitlab.com/networkjanitor/libpolarbytebot
Author: Xyoz Netsphere
Author-email: nanoowl@xyooz.net
License: MIT
Platform: UNKNOWN
Classifier: Development Status :: 3 - Alpha
Classifier: License :: OSI Approved :: MIT License
Classifier: Programming Language :: Python :: 3
Classifier: Programming Language :: Python :: 3.6
Requires-Dist: praw
Requires-Dist: requests
Requires-Dist: SQLAlchemy
Requires-Dist: SQLAlchemy-utils
Requires-Dist: psycopg2
